hyperflask_users/__init__.py
hyperflask_users/blueprint.py
hyperflask_users/captcha.py
hyperflask_users/emails/users/forgot_password.mjml
hyperflask_users/emails/users/login_link.mjml
hyperflask_users/flow.py
hyperflask_users/jinja_ext.py
hyperflask_users/macros.html
hyperflask_users/model.py
hyperflask_users/pages/__init__.py
hyperflask_users/pages/connect.py
hyperflask_users/pages/forgot_password.py
hyperflask_users/pages/login.py
hyperflask_users/pages/login_link.py
hyperflask_users/pages/logout.py
hyperflask_users/pages/reset_password.py
hyperflask_users/pages/signup.py
hyperflask_users/passlib.py
hyperflask_users/signals.py
hyperflask_users/templates/users/auth-layout.html
hyperflask_users/templates/users/connect.html
hyperflask_users/templates/users/forgot_password.html
hyperflask_users/templates/users/login.html
hyperflask_users/templates/users/login_link.html
hyperflask_users/templates/users/recaptcha.html
hyperflask_users/templates/users/reset_password.html
hyperflask_users/templates/users/signup.html
hyperflask_users-0.3.1.dist-info/WHEEL
hyperflask_users-0.3.1.dist-info/entry_points.txt
hyperflask_users-0.3.1.dist-info/METADATA
hyperflask_users-0.3.1.dist-info/RECORD
