Metadata-Version: 2.4
Name: hyperflask-users
Version: 0.3.1
Summary: Authentication and users management for Hyperflask
Author: Maxime Bouroumeau-Fuseau
Author-email: Maxime Bouroumeau-Fuseau <maxime.bouroumeau@gmail.com>
License-Expression: MIT
Requires-Dist: hyperflask>=0.3.0
Requires-Dist: flask-login>=0.6,<1.0
Requires-Dist: passlib>=1.7,<2.0
Requires-Python: >=3.10
Project-URL: Repository, https://github.com/hyperflask/hyperflask-users
